[
    {
        "provider": "Microsoft-Windows-TabletPC-MathRecognizer",
        "event_id": "1",
        "version": "0",
        "event(fields)": "RecognitionStart()",
        "opcode": "Start",
        "keywords": "",
        "task": "Recognition",
        "level": "Informational",
        "evtlog_channel": "",
        "evtlog_message": "",
        "event_fields": []
    },
    {
        "provider": "Microsoft-Windows-TabletPC-MathRecognizer",
        "event_id": "2",
        "version": "0",
        "event(fields)": "RecognitionStop()",
        "opcode": "Stop",
        "keywords": "",
        "task": "Recognition",
        "level": "Informational",
        "evtlog_channel": "",
        "evtlog_message": "",
        "event_fields": []
    },
    {
        "provider": "Microsoft-Windows-TabletPC-MathRecognizer",
        "event_id": "3",
        "version": "0",
        "event(fields)": "RecognitionStrokes(UInt32 intvalue)",
        "opcode": "",
        "keywords": "",
        "task": "RecognitionStrokes",
        "level": "Informational",
        "evtlog_channel": "",
        "evtlog_message": "",
        "event_fields": [
            {
                "field_type": "UInt32",
                "field_name": "intvalue"
            }
        ]
    },
    {
        "provider": "Microsoft-Windows-TabletPC-MathRecognizer",
        "event_id": "4",
        "version": "0",
        "event(fields)": "RecognitionRegions(UInt32 intvalue)",
        "opcode": "",
        "keywords": "",
        "task": "RecognitionRegions",
        "level": "Informational",
        "evtlog_channel": "",
        "evtlog_message": "",
        "event_fields": [
            {
                "field_type": "UInt32",
                "field_name": "intvalue"
            }
        ]
    },
    {
        "provider": "Microsoft-Windows-TabletPC-MathRecognizer",
        "event_id": "5",
        "version": "0",
        "event(fields)": "RecognitionPartitions(UInt32 intvalue)",
        "opcode": "",
        "keywords": "",
        "task": "RecognitionPartitions",
        "level": "Informational",
        "evtlog_channel": "",
        "evtlog_message": "",
        "event_fields": [
            {
                "field_type": "UInt32",
                "field_name": "intvalue"
            }
        ]
    },
    {
        "provider": "Microsoft-Windows-TabletPC-MathRecognizer",
        "event_id": "6",
        "version": "0",
        "event(fields)": "ResetRecognitionContext()",
        "opcode": "",
        "keywords": "",
        "task": "ResetRecognitionContext",
        "level": "Informational",
        "evtlog_channel": "",
        "evtlog_message": "",
        "event_fields": []
    },
    {
        "provider": "Microsoft-Windows-TabletPC-MathRecognizer",
        "event_id": "7",
        "version": "0",
        "event(fields)": "HintApplication()",
        "opcode": "",
        "keywords": "",
        "task": "HintApplication",
        "level": "Informational",
        "evtlog_channel": "",
        "evtlog_message": "",
        "event_fields": []
    },
    {
        "provider": "Microsoft-Windows-TabletPC-MathRecognizer",
        "event_id": "8",
        "version": "0",
        "event(fields)": "ResetLastConstraint()",
        "opcode": "",
        "keywords": "",
        "task": "ResetLastConstraint",
        "level": "Informational",
        "evtlog_channel": "",
        "evtlog_message": "",
        "event_fields": []
    },
    {
        "provider": "Microsoft-Windows-TabletPC-MathRecognizer",
        "event_id": "9",
        "version": "0",
        "event(fields)": "RecognitionFailed()",
        "opcode": "",
        "keywords": "",
        "task": "RecognitionFailed",
        "level": "Informational",
        "evtlog_channel": "",
        "evtlog_message": "",
        "event_fields": []
    },
    {
        "provider": "Microsoft-Windows-TabletPC-MathRecognizer",
        "event_id": "10",
        "version": "0",
        "event(fields)": "RecognitionAlternatesStart()",
        "opcode": "Start",
        "keywords": "",
        "task": "RecognitionAlternates",
        "level": "Informational",
        "evtlog_channel": "",
        "evtlog_message": "",
        "event_fields": []
    },
    {
        "provider": "Microsoft-Windows-TabletPC-MathRecognizer",
        "event_id": "11",
        "version": "0",
        "event(fields)": "RecognitionAlternatesStop()",
        "opcode": "Stop",
        "keywords": "",
        "task": "RecognitionAlternates",
        "level": "Informational",
        "evtlog_channel": "",
        "evtlog_message": "",
        "event_fields": []
    },
    {
        "provider": "Microsoft-Windows-TabletPC-MathRecognizer",
        "event_id": "12",
        "version": "0",
        "event(fields)": "RecognitionTest(UInt32 intvalue)",
        "opcode": "",
        "keywords": "",
        "task": "RecognitionTest",
        "level": "Informational",
        "evtlog_channel": "",
        "evtlog_message": "",
        "event_fields": [
            {
                "field_type": "UInt32",
                "field_name": "intvalue"
            }
        ]
    },
    {
        "provider": "Microsoft-Windows-TabletPC-MathRecognizer",
        "event_id": "13",
        "version": "0",
        "event(fields)": "RecognitionSymbolRecoStart()",
        "opcode": "Start",
        "keywords": "",
        "task": "RecognitionSymbolReco",
        "level": "Informational",
        "evtlog_channel": "",
        "evtlog_message": "",
        "event_fields": []
    },
    {
        "provider": "Microsoft-Windows-TabletPC-MathRecognizer",
        "event_id": "14",
        "version": "0",
        "event(fields)": "RecognitionSymbolRecoStop()",
        "opcode": "Stop",
        "keywords": "",
        "task": "RecognitionSymbolReco",
        "level": "Informational",
        "evtlog_channel": "",
        "evtlog_message": "",
        "event_fields": []
    },
    {
        "provider": "Microsoft-Windows-TabletPC-MathRecognizer",
        "event_id": "15",
        "version": "0",
        "event(fields)": "RecognitionStructureRecoStart()",
        "opcode": "Start",
        "keywords": "",
        "task": "RecognitionStructureReco",
        "level": "Verbose",
        "evtlog_channel": "",
        "evtlog_message": "",
        "event_fields": []
    },
    {
        "provider": "Microsoft-Windows-TabletPC-MathRecognizer",
        "event_id": "16",
        "version": "0",
        "event(fields)": "RecognitionStructureRecoStop()",
        "opcode": "Stop",
        "keywords": "",
        "task": "RecognitionStructureReco",
        "level": "Verbose",
        "evtlog_channel": "",
        "evtlog_message": "",
        "event_fields": []
    },
    {
        "provider": "Microsoft-Windows-TabletPC-MathRecognizer",
        "event_id": "17",
        "version": "0",
        "event(fields)": "ProcessWorkingSetRecognitionBegin(UInt32 intvalue)",
        "opcode": "",
        "keywords": "",
        "task": "ProcessWorkingSetRecognitionBegin",
        "level": "Informational",
        "evtlog_channel": "",
        "evtlog_message": "",
        "event_fields": [
            {
                "field_type": "UInt32",
                "field_name": "intvalue"
            }
        ]
    },
    {
        "provider": "Microsoft-Windows-TabletPC-MathRecognizer",
        "event_id": "18",
        "version": "0",
        "event(fields)": "ProcessWorkingSetRecognitionEnd(UInt32 intvalue)",
        "opcode": "",
        "keywords": "",
        "task": "ProcessWorkingSetRecognitionEnd",
        "level": "Informational",
        "evtlog_channel": "",
        "evtlog_message": "",
        "event_fields": [
            {
                "field_type": "UInt32",
                "field_name": "intvalue"
            }
        ]
    },
    {
        "provider": "Microsoft-Windows-TabletPC-MathRecognizer",
        "event_id": "19",
        "version": "0",
        "event(fields)": "QuickSymbolCorrection()",
        "opcode": "",
        "keywords": "",
        "task": "QuickSymbolCorrection",
        "level": "Informational",
        "evtlog_channel": "",
        "evtlog_message": "",
        "event_fields": []
    },
    {
        "provider": "Microsoft-Windows-TabletPC-MathRecognizer",
        "event_id": "20",
        "version": "0",
        "event(fields)": "CreateMathRecognizerStart()",
        "opcode": "Start",
        "keywords": "",
        "task": "CreateMathRecognizer",
        "level": "Informational",
        "evtlog_channel": "",
        "evtlog_message": "",
        "event_fields": []
    },
    {
        "provider": "Microsoft-Windows-TabletPC-MathRecognizer",
        "event_id": "21",
        "version": "0",
        "event(fields)": "CreateMathRecognizerStop()",
        "opcode": "Stop",
        "keywords": "",
        "task": "CreateMathRecognizer",
        "level": "Informational",
        "evtlog_channel": "",
        "evtlog_message": "",
        "event_fields": []
    },
    {
        "provider": "Microsoft-Windows-TabletPC-MathRecognizer",
        "event_id": "22",
        "version": "0",
        "event(fields)": "PostProcessingRecoResultStart()",
        "opcode": "Start",
        "keywords": "",
        "task": "PostProcessingRecoResult",
        "level": "Informational",
        "evtlog_channel": "",
        "evtlog_message": "",
        "event_fields": []
    },
    {
        "provider": "Microsoft-Windows-TabletPC-MathRecognizer",
        "event_id": "23",
        "version": "0",
        "event(fields)": "PostProcessingRecoResultStop()",
        "opcode": "Stop",
        "keywords": "",
        "task": "PostProcessingRecoResult",
        "level": "Informational",
        "evtlog_channel": "",
        "evtlog_message": "",
        "event_fields": []
    },
    {
        "provider": "Microsoft-Windows-TabletPC-MathRecognizer",
        "event_id": "24",
        "version": "0",
        "event(fields)": "CreateMathRecognizerContextStart()",
        "opcode": "Start",
        "keywords": "",
        "task": "CreateMathRecognizerContext",
        "level": "Informational",
        "evtlog_channel": "",
        "evtlog_message": "",
        "event_fields": []
    },
    {
        "provider": "Microsoft-Windows-TabletPC-MathRecognizer",
        "event_id": "25",
        "version": "0",
        "event(fields)": "CreateMathRecognizerContextStop()",
        "opcode": "Stop",
        "keywords": "",
        "task": "CreateMathRecognizerContext",
        "level": "Informational",
        "evtlog_channel": "",
        "evtlog_message": "",
        "event_fields": []
    }
]